__init__.py
helloworld/__init__.py
helloworld/greeter.py
jeremydimond_python_hello_world-0.0.5.dist-info/licenses/LICENSE
jeremydimond_python_hello_world-0.0.5.dist-info/METADATA
jeremydimond_python_hello_world-0.0.5.dist-info/WHEEL
jeremydimond_python_hello_world-0.0.5.dist-info/entry_points.txt
jeremydimond_python_hello_world-0.0.5.dist-info/top_level.txt
jeremydimond_python_hello_world-0.0.5.dist-info/RECORD
