Metadata-Version: 2.4
Name: jeremydimond.python-hello-world
Version: 0.0.5
Summary: Hello world project to test built, test, publish, etc.
Author-email: Jeremy Dimond <jeremy@jeremydimond.com>
License: Copyright © 2019-2023 Jeremy Dimond
Project-URL: Homepage, https://github.com/jeremydimond/python-hello-world
Keywords: jeremydimond,helloworld,hello,world
Classifier: License :: OSI Approved :: MIT License
Classifier: Programming Language :: Python
Classifier: Programming Language :: Python :: 3
Requires-Python: >=3.9
License-File: LICENSE
Provides-Extra: dev
Requires-Dist: pytest<9.0.0; extra == "dev"
Requires-Dist: pytest-cov; extra == "dev"
Requires-Dist: pytest-tldr; extra == "dev"
Requires-Dist: bumpver; extra == "dev"
Requires-Dist: build; extra == "dev"
Requires-Dist: twine; extra == "dev"
Dynamic: license-file
